kor2vec/__init__.py
kor2vec/__main__.py
kor2vec/context_kor2vec.py
kor2vec/kor2vec.py
kor2vec/dataset/__init__.py
kor2vec/dataset/skip_gram.py
kor2vec/model/__init__.py
kor2vec/model/skip_gram.py
kor2vec/model/vocab.py
kor2vec/model/embedding/__init__.py
kor2vec/model/embedding/word_cnn.py
kor2vec/trainer/__init__.py
kor2vec/trainer/skip_gram.py
kor2vec/utils/__init__.py
kor2vec/utils/build_vocab.py
kor2vec/utils/sampler/__init__.py
kor2vec/utils/sampler/move_sampler.py
kor2vec/utils/sampler/word_sample.py
kor2vec-0.0.1a0.dist-info/DESCRIPTION.rst
kor2vec-0.0.1a0.dist-info/METADATA
kor2vec-0.0.1a0.dist-info/RECORD
kor2vec-0.0.1a0.dist-info/WHEEL
kor2vec-0.0.1a0.dist-info/entry_points.txt
kor2vec-0.0.1a0.dist-info/metadata.json
kor2vec-0.0.1a0.dist-info/top_level.txt
