Metadata-Version: 2.0
Name: kor2vec
Version: 0.0.1a0
Summary: Char-CNN based Korean Word Embedding
Home-page: https://github.com/codertimo/kor2vec
Author: Junseong Kim
Author-email: codertimo@gmail.com
License: UNKNOWN
Platform: UNKNOWN
Classifier: Programming Language :: Python :: 3
Classifier: License :: OSI Approved :: MIT License
Classifier: Operating System :: OS Independent
Requires-Dist: numpy
Requires-Dist: torch (>=0.4.0)
Requires-Dist: tqdm
